.gitignore
README.rst
setup.py
.github/workflows/unit_test-action.yaml
PDIpy.egg-info/PKG-INFO
PDIpy.egg-info/SOURCES.txt
PDIpy.egg-info/dependency_links.txt
PDIpy.egg-info/requires.txt
PDIpy.egg-info/top_level.txt
docs/Makefile
docs/make.bat
docs/source/conf.py
docs/source/index.rst
docs/source/parameter_files.rst
docs/source/pdipy_api.rst
docs/source/pdipy_usage.rst
examples/Beirao_et_al/Beirao_et_al, S_aureus.ipynb
examples/Beirao_et_al/Beirao_et_al, 10 uM solution/inactivation.svg
examples/Beirao_et_al/Beirao_et_al, 10 uM solution/parameters.csv
examples/Beirao_et_al/Beirao_et_al, 10 uM solution/pdipy_input.omex
examples/Beirao_et_al/Beirao_et_al, 10 uM solution/processed_data.csv
examples/Beirao_et_al/Beirao_et_al, 10 uM solution/raw_data.csv
examples/Beirao_et_al/Beirao_et_al, 10 uM solution/variables.csv
examples/Beirao_et_al/Beirao_et_al, 20 uM solution/inactivation.svg
examples/Beirao_et_al/Beirao_et_al, 20 uM solution/parameters.csv
examples/Beirao_et_al/Beirao_et_al, 20 uM solution/pdipy_input.omex
examples/Beirao_et_al/Beirao_et_al, 20 uM solution/processed_data.csv
examples/Beirao_et_al/Beirao_et_al, 20 uM solution/raw_data.csv
examples/Beirao_et_al/Beirao_et_al, 20 uM solution/variables.csv
examples/Beirao_et_al/Beirao_et_al, 5 uM solution/inactivation.svg
examples/Beirao_et_al/Beirao_et_al, 5 uM solution/parameters.csv
examples/Beirao_et_al/Beirao_et_al, 5 uM solution/pdipy_input.omex
examples/Beirao_et_al/Beirao_et_al, 5 uM solution/processed_data.csv
examples/Beirao_et_al/Beirao_et_al, 5 uM solution/raw_data.csv
examples/Beirao_et_al/Beirao_et_al, 5 uM solution/variables.csv
examples/Beirao_et_al/Beirao_et_al, biofilm, 10 uM solution/inactivation.svg
examples/Beirao_et_al/Beirao_et_al, biofilm, 10 uM solution/parameters.csv
examples/Beirao_et_al/Beirao_et_al, biofilm, 10 uM solution/pdipy_input.omex
examples/Beirao_et_al/Beirao_et_al, biofilm, 10 uM solution/processed_data.csv
examples/Beirao_et_al/Beirao_et_al, biofilm, 10 uM solution/raw_data.csv
examples/Beirao_et_al/Beirao_et_al, biofilm, 10 uM solution/variables.csv
