Metadata-Version: 1.0
Name: PDIpy
Version: 0.0.5
Summary: Simulate Photodynamic Inactivation (PDI) of from a kinetics model of membrane oxidation.
Home-page: https://github.com/freiburgermsu/PDIpy
Author: Andrew Freiburger
Author-email: andrewfreiburger@gmail.com
License: MIT
Keywords: antibacterial,photodynamic,biophysics,computational,biology,medicine,PDI,antibiotics
Platform: UNKNOWN
